bicfit/__init__.py
bicfit/models.py
bicfit/plot.py
bicfit/post_fitting.py
bicfit/results/__init__.py
bicfit/results/common.py
bicfit/results/complex_mode.py
bicfit/results/damped_cosine_mode.py
bicfit/results/exponential_decay_mode.py
bicfit/types.py
bicfit-0.2.0.dist-info/WHEEL
bicfit-0.2.0.dist-info/METADATA
bicfit-0.2.0.dist-info/RECORD
