Metadata-Version: 2.3
Name: bicfit
Version: 0.2.0
Summary: General purpose exponential function fitting
Keywords: fit,numerics
Author: Adrien Bocquet
Author-email: Adrien Bocquet <adrienbocquet38@gmail.com>
License:                                  Apache License
Requires-Dist: matplotlib
Requires-Dist: numpy
Requires-Dist: scipy>=1.10.0
Requires-Dist: ruff>=0.8 ; extra == 'dev'
Requires-Dist: pytest>=8.0 ; extra == 'dev'
Requires-Dist: pytest-ordering ; extra == 'dev'
Requires-Dist: pytest-sugar ; extra == 'dev'
Requires-Dist: pytest-xdist ; extra == 'dev'
Requires-Python: >=3.10
Project-URL: Repository, https://github.com/abocquet/bicfit
Provides-Extra: dev
